pysandwich/errors.py
pysandwich/io.py
pysandwich/sandwich.py
pysandwich/tcp_test.py
pysandwich/tunnel.py
pysandwich/tunnel_test.py
pysandwich/proto/errors_pb2.py
pysandwich/proto/io_pb2.py
pysandwich/proto/sandwich_pb2.py
pysandwich/proto/tunnel_pb2.py
pysandwich/proto/api/v1/certificate_pb2.py
pysandwich/proto/api/v1/compliance_pb2.py
pysandwich/proto/api/v1/configuration_pb2.py
pysandwich/proto/api/v1/data_source_pb2.py
pysandwich/proto/api/v1/encoding_format_pb2.py
pysandwich/proto/api/v1/private_key_pb2.py
pysandwich/proto/api/v1/tls_pb2.py
pysandwich/proto/api/v1/tunnel_pb2.py
pysandwich/proto/api/v1/verifiers_pb2.py
pysandwich-0.1.0.dist-info/LICENSE
pysandwich-0.1.0.dist-info/METADATA
pysandwich-0.1.0.dist-info/WHEEL
pysandwich-0.1.0.dist-info/top_level.txt
pysandwich-0.1.0.dist-info/RECORD
