Metadata-Version: 2.1
Name: pysandwich
Version: 0.1.0
Summary: Sandwich Python bindings
Author-email: SandboxAQ <sandwich@sandboxaq.com>
License: AGPL-3.0-only
Project-URL: Homepage, https://github.com/sandbox-quantum/sandwich
License-File: LICENSE
Requires-Dist: protobuf
